tunax/__init__.py
tunax/case.py
tunax/closure.py
tunax/closures/__init__.py
tunax/closures/k_epsilon.py
tunax/closures_registry.py
tunax/database.py
tunax/fitter.py
tunax/functions.py
tunax/model.py
tunax/space.py
tunax-0.2.6.dist-info/LICENSE
tunax-0.2.6.dist-info/METADATA
tunax-0.2.6.dist-info/WHEEL
tunax-0.2.6.dist-info/RECORD
