Metadata-Version: 2.3
Name: tunax
Version: 0.2.6
Summary: Differential calibrator of the vertical ocean turbulence closures.
License: CC BY-NC 4.0
Keywords: ocean,closure,calibration,differential,turbulence
Author: Gabriel Mouttapa
Author-email: gabriel.mouttapa@univ-grenoble-alpes.fr
Requires-Python: >=3.10,<4.0
Classifier: Programming Language :: Python :: 3
Classifier: Operating System :: OS Independent
Requires-Dist: equinox (>=0.11.7)
Requires-Dist: h5py (>=3.12.1)
Requires-Dist: jax (>=0.4.34)
Requires-Dist: jaxtyping (>=0.2.34)
Requires-Dist: netcdf4 (>=1.7.1.post2)
Requires-Dist: optax (>=0.2.3)
Requires-Dist: pyyaml (>=6.0.2,<7.0.0)
Requires-Dist: xarray (>=2024.9.0)
Project-URL: Documentation, https://tunax.readthedocs.io/en/latest/
Project-URL: Issues, https://github.com/meom-group/tunax/issues
Project-URL: Repository, https://github.com/meom-group/tunax
